odoo/addons/account_early_payment_discount/README.rst
odoo/addons/account_early_payment_discount/__init__.py
odoo/addons/account_early_payment_discount/__manifest__.py
odoo/addons/account_early_payment_discount/docs/payment_term_form.png
odoo/addons/account_early_payment_discount/i18n/account_early_payment_discount.pot
odoo/addons/account_early_payment_discount/models/__init__.py
odoo/addons/account_early_payment_discount/models/account_payment_term.py
odoo/addons/account_early_payment_discount/readme/CONFIGURE.rst
odoo/addons/account_early_payment_discount/readme/CONTRIBUTORS.rst
odoo/addons/account_early_payment_discount/readme/DESCRIPTION.rst
odoo/addons/account_early_payment_discount/static/description/icon.png
odoo/addons/account_early_payment_discount/static/description/index.html
odoo/addons/account_early_payment_discount/tests/__init__.py
odoo/addons/account_early_payment_discount/tests/test_payment_term.py
odoo/addons/account_early_payment_discount/views/account_payment_term.xml
odoo12_addon_account_early_payment_discount-12.0.1.0.1.dist-info/METADATA
odoo12_addon_account_early_payment_discount-12.0.1.0.1.dist-info/WHEEL
odoo12_addon_account_early_payment_discount-12.0.1.0.1.dist-info/top_level.txt
odoo12_addon_account_early_payment_discount-12.0.1.0.1.dist-info/RECORD
